gixpy/__init__.py
gixpy/gixpy.py
gixpy/transform.c
gixpy/transform.cp39-win_amd64.pyd
gixpy-5.6.dist-info/LICENSE
gixpy-5.6.dist-info/METADATA
gixpy-5.6.dist-info/WHEEL
gixpy-5.6.dist-info/top_level.txt
gixpy-5.6.dist-info/RECORD
