Metadata-Version: 2.1
Name: gixpy
Version: 5.6
Summary: Transform GIWAXS images
Home-page: https://github.com/ttortorici/gixpy
Author: Teddy Tortorici
Author-email: Teddy Tortorici <edward.tortorici@colorado.edu>
License: GNU GENERAL PUBLIC LICENSE
Project-URL: Homepage, https://github.com/ttortorici/gixpy
Project-URL: Issues, https://github.com/ttortorici/gixpy/issues
Classifier: Programming Language :: Python :: 3
Classifier: Programming Language :: Python :: 3.8
Classifier: Programming Language :: Python :: 3.9
Classifier: Programming Language :: Python :: 3.10
Classifier: Programming Language :: Python :: 3.11
Classifier: License :: OSI Approved :: GNU General Public License v3 (GPLv3)
Classifier: Operating System :: OS Independent
Requires-Python: >=3.8
License-File: LICENSE
Requires-Dist: numpy
Requires-Dist: pyFAI
Requires-Dist: fabio
